<?xml version="1.0" encoding="UTF-8"?>
<metadata xml:lang="en"><Esri><CreaDate>20180323</CreaDate><CreaTime>11514300</CreaTime><ArcGISFormat>1.0</ArcGISFormat><SyncOnce>TRUE</SyncOnce><DataProperties><lineage><Process ToolSource="c:\program files (x86)\arcgis\desktop10.4\ArcToolbox\Toolboxes\Data Management Tools.tbx\CalculateField" Date="20180323" Time="114656">CalculateField points_tall TreeID [TreeID99] VB #</Process><Process ToolSource="c:\program files (x86)\arcgis\desktop10.4\ArcToolbox\Toolboxes\Data Management Tools.tbx\CalculateField" Date="20180323" Time="114725">CalculateField points_tall DBH [DBH99] VB #</Process><Process ToolSource="c:\program files (x86)\arcgis\desktop10.4\ArcToolbox\Toolboxes\Data Management Tools.tbx\CalculateField" Date="20180323" Time="114751">CalculateField points_tall DBH [DBH99] VB #</Process><Process ToolSource="c:\program files (x86)\arcgis\desktop10.4\ArcToolbox\Toolboxes\Data Management Tools.tbx\CalculateField" Date="20180323" Time="114953">CalculateField points_tall TreeID [TreeID99] VB #</Process><Process ToolSource="c:\program files (x86)\arcgis\desktop10.4\ArcToolbox\Toolboxes\Data Management Tools.tbx\CalculateField" Date="20180323" Time="115001">CalculateField points_tall DBH [DBH99] VB #</Process></lineage></DataProperties></Esri></metadata>
